scenario_factory/__init__.py
scenario_factory/builder/__init__.py
scenario_factory/builder/core.py
scenario_factory/builder/dynamic_obstacle_builder.py
scenario_factory/builder/intersection_builder.py
scenario_factory/builder/lanelet_network_builder.py
scenario_factory/builder/planning_problem_builder.py
scenario_factory/builder/scenario_builder.py
scenario_factory/builder/traffic_light_builder.py
scenario_factory/builder/trajectory_builder.py
scenario_factory/ego_vehicle_selection/__init__.py
scenario_factory/ego_vehicle_selection/criterions.py
scenario_factory/ego_vehicle_selection/filters.py
scenario_factory/ego_vehicle_selection/maneuver.py
scenario_factory/ego_vehicle_selection/selection.py
scenario_factory/ego_vehicle_selection/utils.py
scenario_factory/globetrotter/__init__.py
scenario_factory/globetrotter/clustering.py
scenario_factory/globetrotter/filter.py
scenario_factory/globetrotter/osm.py
scenario_factory/globetrotter/region.py
scenario_factory/metrics/__init__.py
scenario_factory/metrics/base.py
scenario_factory/metrics/crime_metric.py
scenario_factory/metrics/general_scenario_metric.py
scenario_factory/metrics/waymo_metric.py
scenario_factory/pipeline/__init__.py
scenario_factory/pipeline/pipeline.py
scenario_factory/pipeline/pipeline_context.py
scenario_factory/pipeline/pipeline_executor.py
scenario_factory/pipeline/pipeline_step.py
scenario_factory/pipeline_steps/__init__.py
scenario_factory/pipeline_steps/criticality.py
scenario_factory/pipeline_steps/globetrotter.py
scenario_factory/pipeline_steps/metrics.py
scenario_factory/pipeline_steps/motion_planning.py
scenario_factory/pipeline_steps/scenario_generation.py
scenario_factory/pipeline_steps/simulation.py
scenario_factory/pipeline_steps/utils.py
scenario_factory/pipeline_steps/visualization_renderer.py
scenario_factory/pipelines.py
scenario_factory/scenario_checker.py
scenario_factory/scenario_config.py
scenario_factory/scenario_container.py
scenario_factory/scenario_features/__init__.py
commonroad_scenario_factory-2.1.0.dist-info/METADATA
commonroad_scenario_factory-2.1.0.dist-info/WHEEL
commonroad_scenario_factory-2.1.0.dist-info/entry_points.txt
commonroad_scenario_factory-2.1.0.dist-info/licenses/LICENSE.txt
commonroad_scenario_factory-2.1.0.dist-info/RECORD
