Metadata-Version: 2.4
Name: commonroad-scenario-factory
Version: 2.1.0
Summary: Automated scenario generation for CommonRoad based on SUMO traffic simulations.
License-Expression: BSD-3-Clause
License-File: LICENSE.txt
Author: Florian Finkeldei
Author-email: florian.finkeldei@tum.de
Requires-Python: >=3.10
Classifier: Programming Language :: Python :: 3
Classifier: Programming Language :: Python :: 3.10
Classifier: Programming Language :: Python :: 3.11
Requires-Dist: click (>=8.1,<9.0)
Requires-Dist: commonroad-clcs (>=2025.1)
Requires-Dist: commonroad-crime (>=0.4.4)
Requires-Dist: commonroad-drivability-checker (>=2025.3.1)
Requires-Dist: commonroad-io (>=2024.3)
Requires-Dist: commonroad-labeling (>=2025.1.1)
Requires-Dist: commonroad-ots (>=2025.1)
Requires-Dist: commonroad-route-planner (>=2025.1.0)
Requires-Dist: commonroad-scenario-designer (>=0.8.5)
Requires-Dist: commonroad-stl-monitor (==2025.1)
Requires-Dist: commonroad-sumo (>=2025.1)
Requires-Dist: iso3166 (>=2.0,<3.0)
Requires-Dist: libsumo (>=1.19,<2.0)
Requires-Dist: multiprocess (>=0.70,<0.71)
Requires-Dist: numpy (>=1.22.4)
Requires-Dist: osmium (>=2.16.0)
Requires-Dist: scikit-learn (>=1.3,<2.0)
Requires-Dist: scipy (>=1.15.3)
Requires-Dist: typing-extensions (>=4.12.2,<5.0.0)
Project-URL: Documentation, https://cps.pages.gitlab.lrz.de/commonroad/scenario-factory/
